<annotation>
	<folder>images</folder>
	<filename>0074 to 0090.png</filename>
	<path>C:\Users\ritika.agarwal\Desktop\ml_images_trial\PointCloud_new\images\0074 to 0090.png</path>
	<source>
		<database>Unknown</database>
	</source>
	<size>
		<width>2610</width>
		<height>431</height>
		<depth>3</depth>
	</size>
	<segmented>0</segmented>
	<object>
		<name>tracks</name>
		<pose>Unspecified</pose>
		<truncated>1</truncated>
		<difficult>0</difficult>
		<bndbox>
			<xmin>1171</xmin>
			<ymin>6</ymin>
			<xmax>1595</xmax>
			<ymax>431</ymax>
		</bndbox>
	</object>
	<object>
		<name>sign</name>
		<pose>Unspecified</pose>
		<truncated>0</truncated>
		<difficult>0</difficult>
		<bndbox>
			<xmin>1786</xmin>
			<ymin>36</ymin>
			<xmax>1871</xmax>
			<ymax>149</ymax>
		</bndbox>
	</object>
	<object>
		<name>pipes</name>
		<pose>Unspecified</pose>
		<truncated>0</truncated>
		<difficult>0</difficult>
		<bndbox>
			<xmin>554</xmin>
			<ymin>4</ymin>
			<xmax>579</xmax>
			<ymax>429</ymax>
		</bndbox>
	</object>
	<object>
		<name>pipes</name>
		<pose>Unspecified</pose>
		<truncated>1</truncated>
		<difficult>0</difficult>
		<bndbox>
			<xmin>599</xmin>
			<ymin>4</ymin>
			<xmax>624</xmax>
			<ymax>431</ymax>
		</bndbox>
	</object>
	<object>
		<name>pipes</name>
		<pose>Unspecified</pose>
		<truncated>1</truncated>
		<difficult>0</difficult>
		<bndbox>
			<xmin>1989</xmin>
			<ymin>34</ymin>
			<xmax>2003</xmax>
			<ymax>431</ymax>
		</bndbox>
	</object>
	<object>
		<name>pipes</name>
		<pose>Unspecified</pose>
		<truncated>1</truncated>
		<difficult>0</difficult>
		<bndbox>
			<xmin>2069</xmin>
			<ymin>34</ymin>
			<xmax>2094</xmax>
			<ymax>431</ymax>
		</bndbox>
	</object>
	<object>
		<name>pipes</name>
		<pose>Unspecified</pose>
		<truncated>1</truncated>
		<difficult>0</difficult>
		<bndbox>
			<xmin>2424</xmin>
			<ymin>21</ymin>
			<xmax>2456</xmax>
			<ymax>431</ymax>
		</bndbox>
	</object>
	<object>
		<name>pipes</name>
		<pose>Unspecified</pose>
		<truncated>1</truncated>
		<difficult>0</difficult>
		<bndbox>
			<xmin>2564</xmin>
			<ymin>19</ymin>
			<xmax>2603</xmax>
			<ymax>431</ymax>
		</bndbox>
	</object>
</annotation>
