<annotation>
	<folder>images</folder>
	<filename>0763 to 0779.png</filename>
	<path>C:\Users\ritika.agarwal\Desktop\ml_images_trial\PointCloud_new\images\0763 to 0779.png</path>
	<source>
		<database>Unknown</database>
	</source>
	<size>
		<width>2614</width>
		<height>432</height>
		<depth>3</depth>
	</size>
	<segmented>0</segmented>
	<object>
		<name>tracks</name>
		<pose>Unspecified</pose>
		<truncated>1</truncated>
		<difficult>0</difficult>
		<bndbox>
			<xmin>1173</xmin>
			<ymin>7</ymin>
			<xmax>1459</xmax>
			<ymax>432</ymax>
		</bndbox>
	</object>
	<object>
		<name>sign</name>
		<pose>Unspecified</pose>
		<truncated>0</truncated>
		<difficult>0</difficult>
		<bndbox>
			<xmin>1793</xmin>
			<ymin>102</ymin>
			<xmax>1876</xmax>
			<ymax>290</ymax>
		</bndbox>
	</object>
	<object>
		<name>green cables</name>
		<pose>Unspecified</pose>
		<truncated>1</truncated>
		<difficult>0</difficult>
		<bndbox>
			<xmin>2443</xmin>
			<ymin>350</ymin>
			<xmax>2521</xmax>
			<ymax>432</ymax>
		</bndbox>
	</object>
	<object>
		<name>pipes</name>
		<pose>Unspecified</pose>
		<truncated>1</truncated>
		<difficult>0</difficult>
		<bndbox>
			<xmin>541</xmin>
			<ymin>1</ymin>
			<xmax>613</xmax>
			<ymax>415</ymax>
		</bndbox>
	</object>
	<object>
		<name>pipes</name>
		<pose>Unspecified</pose>
		<truncated>0</truncated>
		<difficult>0</difficult>
		<bndbox>
			<xmin>846</xmin>
			<ymin>10</ymin>
			<xmax>1016</xmax>
			<ymax>422</ymax>
		</bndbox>
	</object>
	<object>
		<name>pipes</name>
		<pose>Unspecified</pose>
		<truncated>1</truncated>
		<difficult>0</difficult>
		<bndbox>
			<xmin>1971</xmin>
			<ymin>22</ymin>
			<xmax>2004</xmax>
			<ymax>432</ymax>
		</bndbox>
	</object>
	<object>
		<name>pipes</name>
		<pose>Unspecified</pose>
		<truncated>1</truncated>
		<difficult>0</difficult>
		<bndbox>
			<xmin>2051</xmin>
			<ymin>27</ymin>
			<xmax>2157</xmax>
			<ymax>432</ymax>
		</bndbox>
	</object>
</annotation>
